README.rst
setup.py
coroutine/__init__.py
coroutine.egg-info/PKG-INFO
coroutine.egg-info/SOURCES.txt
coroutine.egg-info/dependency_links.txt
coroutine.egg-info/top_level.txt
coroutine.egg-info/zip-safe
coroutine/components/__init__.py
coroutine/components/future.py
coroutine/components/generator_adapter.py
coroutine/components/kqueue.py
coroutine/components/select.py
coroutine/components/timeout.py
coroutine/components/utils.py
coroutine/components/waker.py
coroutine/loop/__init__.py
coroutine/loop/event_loop.py
test/test_coroutine.py
test/test_event_loop_for_all_python.py
test/test_event_loop_for_python3_only.py
test/test_generator.py