Metadata-Version: 1.1
Name: coroutine
Version: 0.0.2
Summary: simple coroutine event loop. 
Home-page: https://www.github.com/ShichaoMa/toolkit
Author: cn
Author-email: cnaafhvk@foxmail.com
License: MIT
Keywords: coroutine event loop
Platform: UNKNOWN
Classifier: License :: OSI Approved :: MIT License
Classifier: Programming Language :: Python
Classifier: Intended Audience :: Developers
Classifier: Operating System :: OS Independent
